pyrevdns/__init__.py
pyrevdns/__main__.py
pyrevdns/arg_parser.py
pyrevdns/pyrevdns.py
pyrevdns-1.0.1.dist-info/LICENSE.md
pyrevdns-1.0.1.dist-info/METADATA
pyrevdns-1.0.1.dist-info/WHEEL
pyrevdns-1.0.1.dist-info/top_level.txt
pyrevdns-1.0.1.dist-info/RECORD
