Metadata-Version: 2.1
Name: pyrevdns
Version: 1.0.1
Summary: PYrevDNS is a simple tool for performing reverse DNS lookups on IP addresses.
Author-email: Shivam Saraswat <thecybersapien@protonmail.com>
License: MIT License
Project-URL: repository, https://github.com/shivamsaraswat/pyrevdns
Requires-Python: >=3.10
License-File: LICENSE.md
Requires-Dist: dnspython
